site_packages_packer/__init__.py
site_packages_packer/core.py
site_packages_packer-0.0.7.dist-info/LICENSE
site_packages_packer-0.0.7.dist-info/METADATA
site_packages_packer-0.0.7.dist-info/WHEEL
site_packages_packer-0.0.7.dist-info/entry_points.txt
site_packages_packer-0.0.7.dist-info/top_level.txt
site_packages_packer-0.0.7.dist-info/RECORD
