Metadata-Version: 2.1
Name: site-packages-packer
Version: 0.0.7
Summary: Pack selected packages from site-packages and output license file
Home-page: https://github.com/kawaidev/site-packages-packer
Author: kawaidev
Author-email: kawai.dev.py@gmail.com
License: MIT
Platform: UNKNOWN
Requires-Python: >=3.7
Requires-Dist: pip-licenses (~=3.3.0)
